[
  {
    "nev": "R\u00f3kagombaleves",
    "elkeszites": "15 perc",
    "fozes": "40 perc",
    "kaloria": "440 kcl / adag",
    "kep": "/gombak/receptek/roka/1.kep.jpeg",
    "link": "https://www.nosalty.hu/recept/rokagombagomba-leves"
  },
  {
    "nev": "Feh\u00e9rboros r\u00f3kagomba",
    "elkeszites": "5 perc",
    "fozes": "10 perc",
    "kaloria": "348 kcl / adag",
    "kep": "/gombak/receptek/roka/2.kep.jpeg",
    "link": "https://www.nosalty.hu/recept/feherboros-rokagomba"
  },
  {
    "nev": "R\u00f3kagomb\u00e1s tagliatelle",
    "elkeszites": "30 perc",
    "fozes": "6 perc",
    "kaloria": "800 kcl / adag",
    "kep": "/gombak/receptek/roka/3.kep.jpeg",
    "link": "https://www.nosalty.hu/recept/rokagombas-tagliatelle"
  }
]
